gsv86lib/CSVwriter.py
gsv86lib/GSV6_AnfrageCodes.py
gsv86lib/GSV6_BasicFrameType.py
gsv86lib/GSV6_ErrorCodes.py
gsv86lib/GSV6_FrameRouter.py
gsv86lib/GSV6_MessFrameHandler.py
gsv86lib/GSV6_Protocol.py
gsv86lib/GSV6_SeriallLib.py
gsv86lib/GSV6_UnitCodes.py
gsv86lib/GSV_BasicMeasurement.py
gsv86lib/GSV_Exceptions.py
gsv86lib/ThreadSafeVar.py
gsv86lib/__init__.py
gsv86lib/gsv86.py
gsv86lib-0.1.0.dist-info/licenses/LICENSE
gsv86lib-0.1.0.dist-info/METADATA
gsv86lib-0.1.0.dist-info/WHEEL
gsv86lib-0.1.0.dist-info/top_level.txt
gsv86lib-0.1.0.dist-info/RECORD
