Metadata-Version: 2.4
Name: gsv86lib
Version: 0.1.0
Summary: Python library for ME-Systeme GSV-8 and GSV-6 (wrapped from gsv8pypi_python3)
Author: ME-Systeme GmbH
License: The MIT License (MIT)
Project-URL: Homepage, https://github.com/me-systeme/gsv86lib
Classifier: Programming Language :: Python :: 3
Classifier: License :: OSI Approved :: MIT License
Classifier: Operating System :: OS Independent
Requires-Python: >=3.8
License-File: LICENSE
Requires-Dist: pyserial>=3.5
Dynamic: license-file
